app_toggles/__init__.py
app_toggles/_exceptions.py
app_toggles/_toggle_providers/__init__.py
app_toggles/_toggle_providers/json_toggle_provider.py
app_toggles/_toggle_providers/provider.py
app_toggles/_toggles.py
app_toggles/_types.py
app_toggles-0.1.2.dist-info/LICENSE
app_toggles-0.1.2.dist-info/METADATA
app_toggles-0.1.2.dist-info/WHEEL
app_toggles-0.1.2.dist-info/RECORD
