Metadata-Version: 2.1
Name: app-toggles
Version: 0.1.2
Summary: A library to manage app toggles
Author: Gustavo Eguez
Author-email: eguezgustavo@gmail.com
Requires-Python: >=3.10,<4.0
Classifier: Programming Language :: Python :: 3
Classifier: Programming Language :: Python :: 3.10
Classifier: Programming Language :: Python :: 3.11
Requires-Dist: black (>=23.7.0,<24.0.0)
